_fir1.cp310-win_amd64.pyd
fir1.py
fir1-1.7.1.1.dist-info/AUTHORS
fir1-1.7.1.1.dist-info/COPYING
fir1-1.7.1.1.dist-info/METADATA
fir1-1.7.1.1.dist-info/WHEEL
fir1-1.7.1.1.dist-info/top_level.txt
fir1-1.7.1.1.dist-info/RECORD
