Metadata-Version: 2.1
Name: fir1
Version: 1.7.1.1
Summary: Efficient FIR realtime filter
Home-page: https://github.com/berndporr/fir1
Author: Bernd Porr
Author-email: mail@berndporr.me.uk
License: MIT
Platform: UNKNOWN
Classifier: Intended Audience :: Developers
Classifier: Operating System :: POSIX
Classifier: Operating System :: Microsoft :: Windows
Classifier: Programming Language :: Python :: 3
License-File: COPYING
License-File: AUTHORS
Requires-Dist: numpy
